<?xml version="1.0"?>
<ArrayOfDrone xmlns:xsi="http://www.w3.org/2001/XMLSchema-instance" xmlns:xsd="http://www.w3.org/2001/XMLSchema">
  <Drone>
    <Id>1</Id>
    <Model>Kud</Model>
    <Weight>Medium</Weight>
  </Drone>
  <Drone>
    <Id>2</Id>
    <Model>Ppf</Model>
    <Weight>Light</Weight>
  </Drone>
  <Drone>
    <Id>3</Id>
    <Model>Lfr</Model>
    <Weight>Medium</Weight>
  </Drone>
  <Drone>
    <Id>4</Id>
    <Model>Yuy</Model>
    <Weight>Medium</Weight>
  </Drone>
  <Drone>
    <Id>5</Id>
    <Model>Hee</Model>
    <Weight>Medium</Weight>
  </Drone>
  <Drone>
    <Id>6</Id>
    <Model>Vmc</Model>
    <Weight>Light</Weight>
  </Drone>
  <Drone>
    <Id>7</Id>
    <Model>Mvj</Model>
    <Weight>Medium</Weight>
  </Drone>
  <Drone>
    <Id>8</Id>
    <Model>Aij</Model>
    <Weight>Light</Weight>
  </Drone>
  <Drone>
    <Id>9</Id>
    <Model>Ohq</Model>
    <Weight>Light</Weight>
  </Drone>
  <Drone>
    <Id>10</Id>
    <Model>Icu</Model>
    <Weight>Light</Weight>
  </Drone>
  <Drone>
    <Id>11</Id>
    <Model>Ted</Model>
    <Weight>Light</Weight>
  </Drone>
  <Drone>
    <Id>12</Id>
    <Model>Nyv</Model>
    <Weight>Light</Weight>
  </Drone>
  <Drone>
    <Id>13</Id>
    <Model>Svg</Model>
    <Weight>Medium</Weight>
  </Drone>
  <Drone>
    <Id>14</Id>
    <Model>Xti</Model>
    <Weight>Medium</Weight>
  </Drone>
  <Drone>
    <Id>15</Id>
    <Model>Rag</Model>
    <Weight>Medium</Weight>
  </Drone>
</ArrayOfDrone>